CHANGES
LICENSE
MANIFEST.in
setup.py
diffantom/EXAMPLES.rst
diffantom/__init__.py
diffantom/info.py
diffantom/interfaces.py
diffantom/utils.py
diffantom/workflows.py
diffantom.egg-info/PKG-INFO
diffantom.egg-info/SOURCES.txt
diffantom.egg-info/dependency_links.txt
diffantom.egg-info/entry_points.txt
diffantom.egg-info/not-zip-safe
diffantom.egg-info/requires.txt
diffantom.egg-info/top_level.txt
diffantom/data/bedpostx.json
diffantom/scripts/__init__.py
diffantom/scripts/diffantom.py
diffantom/scripts/sticks2dwis.py