Metadata-Version: 1.1
Name: diffantom
Version: 1.0.1
Summary: 
Home-page: https://github.com/oesteban/diffantom
Author: Oscar Esteban
Author-email: code@oscaresteban.es
License: MIT License
Download-URL: https://pypi.python.org/packages/source/d/diffantom/diffantom-1.0.1.tar.gz
Platform: UNKNOWN
Classifier: Development Status :: 4 - Beta
Classifier: Intended Audience :: Science/Research
Classifier: Topic :: Scientific/Engineering :: Image Recognition
Classifier: License :: OSI Approved :: MIT License
Classifier: Programming Language :: Python :: 2.7
